posty/__init__.py
posty/posty.py
i_posty-1.0.0.dist-info/LICENSE
i_posty-1.0.0.dist-info/METADATA
i_posty-1.0.0.dist-info/WHEEL
i_posty-1.0.0.dist-info/entry_points.txt
i_posty-1.0.0.dist-info/top_level.txt
i_posty-1.0.0.dist-info/RECORD
