Metadata-Version: 2.1
Name: i-posty
Version: 1.0.0
Summary: A lightweight command-line link shortening tool for Linux.
Home-page: https://github.com/not-so-cool-anymore/posty/
Author: Ivan Zlatanov
Author-email: i_zlatanov@protonmail.com
License: UNKNOWN
Platform: UNKNOWN
Classifier: Programming Language :: Python :: 3
Classifier: License :: OSI Approved :: GNU General Public License v3 or later (GPLv3+)
Classifier: Operating System :: OS Independent
Requires-Python: >=3.0
